plover_next_stroke/config_ui.py
plover_next_stroke/next_stroke_config.py
plover_next_stroke/next_stroke_macros.py
plover_next_stroke/next_stroke_suggestions.py
plover_next_stroke/next_stroke_ui.py
plover_next_stroke/resources_rc.py
plover_next_stroke/sorting.py
plover_next_stroke-0.2.2.dist-info/LICENSE.txt
plover_next_stroke-0.2.2.dist-info/METADATA
plover_next_stroke-0.2.2.dist-info/WHEEL
plover_next_stroke-0.2.2.dist-info/entry_points.txt
plover_next_stroke-0.2.2.dist-info/top_level.txt
plover_next_stroke-0.2.2.dist-info/zip-safe
plover_next_stroke-0.2.2.dist-info/RECORD
